IGJSP/generador.py
IGJSP/main.py
IGJSP/Minizinc/Models/RD/JSP0.mzn
IGJSP/Minizinc/Models/RD/JSP1.mzn
IGJSP/Minizinc/Models/RD/JSP2.mzn
IGJSP/Minizinc/Types/RD/JSP0.mzn
IGJSP/Minizinc/Types/RD/JSP1.mzn
IGJSP/Minizinc/Types/RD/JSP2.mzn
IGJSP/Minizinc/Types/RD/FJSP/type0.dzn
IGJSP/Minizinc/Types/RD/FJSP/type1.dzn
IGJSP/Minizinc/Types/RD/FJSP/type2.dzn
IGJSP/Minizinc/Types/RD/JSP/type0.dzn
IGJSP/Minizinc/Types/RD/JSP/type1.dzn
IGJSP/Minizinc/Types/RD/JSP/type2.dzn
igjsp-1.1.10.dist-info/METADATA
igjsp-1.1.10.dist-info/WHEEL
igjsp-1.1.10.dist-info/licenses/LICENSE
igjsp-1.1.10.dist-info/RECORD
