Metadata-Version: 2.4
Name: IGJSP
Version: 1.1.10
Summary: Instance generator for JSP
Project-URL: Homepage, https://gps.blogs.upv.es/
Author-email: GPS-UPV <gps@dsic.upv.es>
License-File: LICENSE
Classifier: License :: OSI Approved :: MIT License
Classifier: Operating System :: OS Independent
Classifier: Programming Language :: Python :: 3
Requires-Python: >=3.9
Requires-Dist: numpy
Requires-Dist: scipy
